[
  {
    "title": "Doctor Who: uma viagem pelos 50 anos de jogos da série",
    "link": "https://www.gameblast.com.br/2013/11/allons-y-vamos-comemorar-os-50-anos-de.html"
  },
  {
    "title": "Máquinas do tempo: as 10 melhores segundo os videogames",
    "link": "http://www.gameblast.com.br/2014/06/maquina-tempo-videogame.html"
  },
  {
    "title": "Tão nacionais quanto samba e futebol: conheça os jogos brasileiros do Master System",
    "link": "https://www.gameblast.com.br/2013/08/tao-nacionais-quanto-samba-e-futebol.html"
  },
  {
    "title": "O pulo duplo e a sua (im)possibilidade científica",
    "link": "https://www.gameblast.com.br/2015/05/pulo-duplo-ciencia.html"
  },
  {
    "title": "Portal Gun: entenda a “ciência” por trás dessa arma",
    "link": "https://www.gameblast.com.br/2015/04/portal-gun-ciencia.html"
  },
  {
    "title": "Bem-vindo ao Centro de Enriquecimento da Aperture Science Laboratories!",
    "link": "https://www.gameblast.com.br/2013/04/bem-vindo-ao-centro-de-enriquecimento.html"
  },
  {
    "title": "Blast from the Past: Splash (Web)",
    "link": "https://www.gameblast.com.br/2013/03/blast-from-past-splash-web.html"
  },
  {
    "title": "Reclamando do PS4? Veja por quanto os consoles foram lançados no Brasil durante a história",
    "link": "https://www.gameblast.com.br/2013/10/reclamando-do-ps4-veja-por-quanto-os.html"
  },
  {
    "title": "Um papo com Marcos Lima: sonoplastia para jogos e Orquestra Multiplayer",
    "link": "https://www.gameblast.com.br/2015/07/marcos-lima-entrevista.html"
  }
]